[{
  "_id": {
    "$oid": "661002d73ff31cc7d572a41c"
  },
  "name": "Ngôn tình",
  "books": [
    {
      "$oid": "6610db3712f5138eb54eb08a"
    },
    {
      "$oid": "66112fe262f902a02569c461"
    },
    {
      "$oid": "6611303e62f902a02569c46d"
    },
    {
      "$oid": "6611314d62f902a02569c485"
    },
    {
      "$oid": "661132fa62f902a02569c4d8"
    },
    {
      "$oid": "6611348c62f902a02569c573"
    },
    {
      "$oid": "6611355762f902a02569c57f"
    }
  ],
  "__v": 0
},
{
  "_id": {
    "$oid": "661003033ff31cc7d572a420"
  },
  "name": "Trinh thám - Kinh dị",
  "books": [
    {
      "$oid": "6610dbb212f5138eb54eb0a6"
    },
    {
      "$oid": "661130a062f902a02569c479"
    },
    {
      "$oid": "661133b862f902a02569c4e4"
    }
  ],
  "__v": 0
},
{
  "_id": {
    "$oid": "6610036c3ff31cc7d572a423"
  },
  "name": "Sức khỏe - Làm đẹp",
  "books": [
    {
      "$oid": "6611361062f902a02569c596"
    }
  ],
  "__v": 0
},
{
  "_id": {
    "$oid": "661003973ff31cc7d572a426"
  },
  "name": "Truyện - Tiểu thuyết",
  "books": [
    {
      "$oid": "661135b262f902a02569c58a"
    }
  ],
  "__v": 0
},
{
  "_id": {
    "$oid": "66124b127db9a6069958d54d"
  },
  "name": "Tâm Linh - Tôn Giáo",
  "books": [
    {
      "$oid": "66124bd17db9a6069958d616"
    }
  ],
  "__v": 0
},
{
  "_id": {
    "$oid": "6612a9c0917e29e62d0ca87d"
  },
  "name": "Phát Triển Cá Nhân",
  "books": [
    {
      "$oid": "6612aa1f917e29e62d0ca8ae"
    }
  ],
  "__v": 0
},
{
  "_id": {
    "$oid": "6613d1bb3122421ac2271d20"
  },
  "name": "Giáo dục - Văn hóa & Xã hội",
  "books": [
    {
      "$oid": "6613d22d3122421ac2271d50"
    },
    {
      "$oid": "661734457e64d3da4f065a14"
    }
  ],
  "__v": 0
}]